{
  "name": "PHSC",
  "courses": [
    {
      "code": "PHSC388D",
      "name": "Special Topics in Public Health Science; Moving Fearlessly Forward: The Pursuit of Career Success in Public Health Science",
      "credits": {
        "Amount": 1
      },
      "gen_eds": null,
      "description": "This course will illustrate and investigate the relationship between experiential learning and career readiness in public health. Primarily through listening to relevant podcasts, students will reflect on their skill development, think critically about industry trends, and identify best practices for success in the public health workforce. Students will bridge the gap between their current skills and their career aspirations through strategic planning of curricular and co-curricular engagement. Student learning will culminate in the creation of a career roadmap- an individualized action plan to move fearlessly forward into career success.",
      "sections": [
        {
          "sec_code": "0101",
          "instructors": [
            "Shannon Edward"
          ],
          "class_meetings": [
            {
              "InPerson": {
                "classtime": {
                  "W": [
                    [
                      10,
                      0,
                      "Am"
                    ],
                    [
                      10,
                      50,
                      "Am"
                    ]
                  ]
                },
                "location": [
                  "SPH",
                  "0307"
                ]
              }
            },
            "OnlineAsync"
          ]
        }
      ]
    },
    {
      "code": "PHSC388F",
      "name": "Special Topics in Public Health Science; The Public Health Lessons of the COVID-19 Pandemic: A Retrospective Examination",
      "credits": {
        "Amount": 3
      },
      "gen_eds": null,
      "description": "The long-term social impacts of the COVID-19 pandemic are only now beginning to become evident, especially with regards to public health policy and practices. This course will provide a retrospective analysis of the pandemic from a variety of social and public health perspectives with the aim of discussing what went right, what went wrong, and how these perspectives may shape future pandemic preparedness and public health policies and practices. Students will be introduced to a variety of topics related to the pandemic to gain the proper background and context for further discussion, such as the history of previous pandemics, the biology of SARS-CoV-2 and the major players in governmental policy and decision-making processes. Students will then examine the major policy and health-practice related decisions made during the pandemic and discuss the positive and negative impacts of these decisions from a variety of perspectives, including their own lived experience. Using the knowledge and perspectives gained during these discussions, students will draft their own pandemic policy and action plan in response to a hypothetical future pandemic.",
      "sections": [
        {
          "sec_code": "0101",
          "instructors": [
            "Instructor: TBA"
          ],
          "class_meetings": [
            {
              "InPerson": {
                "classtime": {
                  "TuTh": [
                    [
                      9,
                      30,
                      "Am"
                    ],
                    [
                      10,
                      45,
                      "Am"
                    ]
                  ]
                },
                "location": [
                  "SPH",
                  "0227"
                ]
              }
            }
          ]
        }
      ]
    },
    {
      "code": "PHSC389",
      "name": "Independent Research Study in Public Health Science",
      "credits": {
        "Range": [
          1,
          6
        ]
      },
      "gen_eds": null,
      "description": "",
      "sections": [
        {
          "sec_code": "0101",
          "instructors": [
            "Shannon Edward"
          ],
          "class_meetings": [
            "Unspecified"
          ]
        },
        {
          "sec_code": "1",
          "instructors": [
            "Shannon Edward"
          ],
          "class_meetings": [
            "Unspecified"
          ]
        }
      ]
    },
    {
      "code": "PHSC399",
      "name": "Public Health Science Internship",
      "credits": {
        "Range": [
          1,
          6
        ]
      },
      "gen_eds": null,
      "description": "",
      "sections": [
        {
          "sec_code": "0101",
          "instructors": [
            "Shannon Edward"
          ],
          "class_meetings": [
            "Unspecified"
          ]
        },
        {
          "sec_code": "1",
          "instructors": [
            "Shannon Edward"
          ],
          "class_meetings": [
            "Unspecified"
          ]
        }
      ]
    },
    {
      "code": "PHSC415",
      "name": "Essentials of Public Health Biology: The Cell, The Individual, and Disease",
      "credits": {
        "Amount": 3
      },
      "gen_eds": null,
      "description": "Presents the basic scientific and biomedical concepts of modern public health problems and explores in depth mechanisms and models of the major categories of disease. The biologic principles presented are foundations to public health disease prevention, control, or management programs.",
      "sections": [
        {
          "sec_code": "0101",
          "instructors": [
            "Jessica O'Hara"
          ],
          "class_meetings": [
            {
              "InPerson": {
                "classtime": {
                  "W": [
                    [
                      1,
                      0,
                      "Pm"
                    ],
                    [
                      1,
                      50,
                      "Pm"
                    ]
                  ]
                },
                "location": [
                  "SPH",
                  "1312"
                ]
              }
            },
            "OnlineAsync",
            {
              "InPerson": {
                "classtime": {
                  "W": [
                    [
                      2,
                      0,
                      "Pm"
                    ],
                    [
                      2,
                      50,
                      "Pm"
                    ]
                  ]
                },
                "location": [
                  "SPH",
                  "1301"
                ]
              }
            }
          ]
        },
        {
          "sec_code": "0102",
          "instructors": [
            "Jessica O'Hara"
          ],
          "class_meetings": [
            {
              "InPerson": {
                "classtime": {
                  "W": [
                    [
                      1,
                      0,
                      "Pm"
                    ],
                    [
                      1,
                      50,
                      "Pm"
                    ]
                  ]
                },
                "location": [
                  "SPH",
                  "1312"
                ]
              }
            },
            "OnlineAsync",
            {
              "InPerson": {
                "classtime": {
                  "Th": [
                    [
                      11,
                      0,
                      "Am"
                    ],
                    [
                      11,
                      50,
                      "Am"
                    ]
                  ]
                },
                "location": [
                  "SPH",
                  "1301"
                ]
              }
            }
          ]
        },
        {
          "sec_code": "0103",
          "instructors": [
            "Jessica O'Hara"
          ],
          "class_meetings": [
            {
              "InPerson": {
                "classtime": {
                  "W": [
                    [
                      1,
                      0,
                      "Pm"
                    ],
                    [
                      1,
                      50,
                      "Pm"
                    ]
                  ]
                },
                "location": [
                  "SPH",
                  "1312"
                ]
              }
            },
            "OnlineAsync",
            {
              "InPerson": {
                "classtime": {
                  "Th": [
                    [
                      12,
                      30,
                      "Pm"
                    ],
                    [
                      1,
                      20,
                      "Pm"
                    ]
                  ]
                },
                "location": [
                  "SPH",
                  "1301"
                ]
              }
            }
          ]
        },
        {
          "sec_code": "0104",
          "instructors": [
            "Jessica O'Hara"
          ],
          "class_meetings": [
            {
              "InPerson": {
                "classtime": {
                  "W": [
                    [
                      1,
                      0,
                      "Pm"
                    ],
                    [
                      1,
                      50,
                      "Pm"
                    ]
                  ]
                },
                "location": [
                  "SPH",
                  "1312"
                ]
              }
            },
            "OnlineAsync",
            {
              "InPerson": {
                "classtime": {
                  "Th": [
                    [
                      2,
                      0,
                      "Pm"
                    ],
                    [
                      2,
                      50,
                      "Pm"
                    ]
                  ]
                },
                "location": [
                  "SPH",
                  "1301"
                ]
              }
            }
          ]
        },
        {
          "sec_code": "0105",
          "instructors": [
            "Jessica O'Hara"
          ],
          "class_meetings": [
            {
              "InPerson": {
                "classtime": {
                  "W": [
                    [
                      1,
                      0,
                      "Pm"
                    ],
                    [
                      1,
                      50,
                      "Pm"
                    ]
                  ]
                },
                "location": [
                  "SPH",
                  "1312"
                ]
              }
            },
            "OnlineAsync",
            {
              "InPerson": {
                "classtime": {
                  "Th": [
                    [
                      3,
                      0,
                      "Pm"
                    ],
                    [
                      3,
                      50,
                      "Pm"
                    ]
                  ]
                },
                "location": [
                  "SPH",
                  "1301"
                ]
              }
            }
          ]
        }
      ]
    },
    {
      "code": "PHSC450",
      "name": "Addressing Social and Structural Inequities Through Public Health",
      "credits": {
        "Amount": 3
      },
      "gen_eds": [
        "DVUP"
      ],
      "description": "A focus on addressing social and structural inequities within race, gender, disability, and class through various perspectives in the field of public health. Students explore the causes, challenges, consequences, and extent these injustices have on health disparities from local, national, and global perspectives. Students view these inequities through the lens of the affected populations, and work interactively and collaboratively to interpret, design, and evaluate public health interventions and approaches to address key health disparities within specific communities. The aim of this course is to help students define appropriate research and address structural inequities with innovative approaches through the professional practice of public health.",
      "sections": [
        {
          "sec_code": "0101",
          "instructors": [
            "Kendall Bustad"
          ],
          "class_meetings": [
            {
              "InPerson": {
                "classtime": {
                  "MW": [
                    [
                      3,
                      0,
                      "Pm"
                    ],
                    [
                      3,
                      50,
                      "Pm"
                    ]
                  ]
                },
                "location": [
                  "ESJ",
                  "0202"
                ]
              }
            },
            {
              "InPerson": {
                "classtime": {
                  "Th": [
                    [
                      8,
                      0,
                      "Am"
                    ],
                    [
                      8,
                      50,
                      "Am"
                    ]
                  ]
                },
                "location": [
                  "SPH",
                  "0305"
                ]
              }
            }
          ]
        },
        {
          "sec_code": "0102",
          "instructors": [
            "Kendall Bustad"
          ],
          "class_meetings": [
            {
              "InPerson": {
                "classtime": {
                  "MW": [
                    [
                      3,
                      0,
                      "Pm"
                    ],
                    [
                      3,
                      50,
                      "Pm"
                    ]
                  ]
                },
                "location": [
                  "ESJ",
                  "0202"
                ]
              }
            },
            {
              "InPerson": {
                "classtime": {
                  "Th": [
                    [
                      9,
                      30,
                      "Am"
                    ],
                    [
                      10,
                      20,
                      "Am"
                    ]
                  ]
                },
                "location": [
                  "SPH",
                  "0305"
                ]
              }
            }
          ]
        },
        {
          "sec_code": "0103",
          "instructors": [
            "Kendall Bustad"
          ],
          "class_meetings": [
            {
              "InPerson": {
                "classtime": {
                  "MW": [
                    [
                      3,
                      0,
                      "Pm"
                    ],
                    [
                      3,
                      50,
                      "Pm"
                    ]
                  ]
                },
                "location": [
                  "ESJ",
                  "0202"
                ]
              }
            },
            {
              "InPerson": {
                "classtime": {
                  "Th": [
                    [
                      11,
                      0,
                      "Am"
                    ],
                    [
                      11,
                      50,
                      "Am"
                    ]
                  ]
                },
                "location": [
                  "SPH",
                  "0305"
                ]
              }
            }
          ]
        },
        {
          "sec_code": "0104",
          "instructors": [
            "Kendall Bustad"
          ],
          "class_meetings": [
            {
              "InPerson": {
                "classtime": {
                  "MW": [
                    [
                      3,
                      0,
                      "Pm"
                    ],
                    [
                      3,
                      50,
                      "Pm"
                    ]
                  ]
                },
                "location": [
                  "ESJ",
                  "0202"
                ]
              }
            },
            {
              "InPerson": {
                "classtime": {
                  "Th": [
                    [
                      12,
                      30,
                      "Pm"
                    ],
                    [
                      1,
                      20,
                      "Pm"
                    ]
                  ]
                },
                "location": [
                  "SPH",
                  "0305"
                ]
              }
            }
          ]
        },
        {
          "sec_code": "0105",
          "instructors": [
            "Kendall Bustad"
          ],
          "class_meetings": [
            {
              "InPerson": {
                "classtime": {
                  "MW": [
                    [
                      3,
                      0,
                      "Pm"
                    ],
                    [
                      3,
                      50,
                      "Pm"
                    ]
                  ]
                },
                "location": [
                  "ESJ",
                  "0202"
                ]
              }
            },
            {
              "InPerson": {
                "classtime": {
                  "Th": [
                    [
                      2,
                      0,
                      "Pm"
                    ],
                    [
                      2,
                      50,
                      "Pm"
                    ]
                  ]
                },
                "location": [
                  "SPH",
                  "0305"
                ]
              }
            }
          ]
        },
        {
          "sec_code": "0106",
          "instructors": [
            "Kendall Bustad"
          ],
          "class_meetings": [
            {
              "InPerson": {
                "classtime": {
                  "MW": [
                    [
                      3,
                      0,
                      "Pm"
                    ],
                    [
                      3,
                      50,
                      "Pm"
                    ]
                  ]
                },
                "location": [
                  "ESJ",
                  "0202"
                ]
              }
            },
            {
              "InPerson": {
                "classtime": {
                  "Th": [
                    [
                      3,
                      30,
                      "Pm"
                    ],
                    [
                      4,
                      20,
                      "Pm"
                    ]
                  ]
                },
                "location": [
                  "SPH",
                  "0305"
                ]
              }
            }
          ]
        },
        {
          "sec_code": "0107",
          "instructors": [
            "Kendall Bustad"
          ],
          "class_meetings": [
            {
              "InPerson": {
                "classtime": {
                  "MW": [
                    [
                      3,
                      0,
                      "Pm"
                    ],
                    [
                      3,
                      50,
                      "Pm"
                    ]
                  ]
                },
                "location": [
                  "ESJ",
                  "0202"
                ]
              }
            },
            {
              "InPerson": {
                "classtime": {
                  "F": [
                    [
                      10,
                      0,
                      "Am"
                    ],
                    [
                      10,
                      50,
                      "Am"
                    ]
                  ]
                },
                "location": [
                  "SPH",
                  "0121"
                ]
              }
            }
          ]
        },
        {
          "sec_code": "0108",
          "instructors": [
            "Kendall Bustad"
          ],
          "class_meetings": [
            {
              "InPerson": {
                "classtime": {
                  "MW": [
                    [
                      3,
                      0,
                      "Pm"
                    ],
                    [
                      3,
                      50,
                      "Pm"
                    ]
                  ]
                },
                "location": [
                  "ESJ",
                  "0202"
                ]
              }
            },
            {
              "InPerson": {
                "classtime": {
                  "F": [
                    [
                      11,
                      0,
                      "Am"
                    ],
                    [
                      11,
                      50,
                      "Am"
                    ]
                  ]
                },
                "location": [
                  "SPH",
                  "0121"
                ]
              }
            }
          ]
        },
        {
          "sec_code": "1",
          "instructors": [
            "Kendall Bustad"
          ],
          "class_meetings": [
            "OnlineAsync",
            {
              "OnlineSync": {
                "Th": [
                  [
                    10,
                    0,
                    "Am"
                  ],
                  [
                    10,
                    50,
                    "Am"
                  ]
                ]
              }
            }
          ]
        }
      ]
    },
    {
      "code": "PHSC497",
      "name": "Public Health Science Capstone",
      "credits": {
        "Amount": 3
      },
      "gen_eds": [
        "DSSP"
      ],
      "description": "The capstone course is the culminating experience for Public Health Science students and must be taken only in the final semester of study. The Public Health Science capstone course is designed to challenge students to integrate the five core areas of public health in investigating, researching and addressing public health issues. Throughout the semester, students will be required to evaluate, analyze and synthesize scholarly works as they research and propose solutions to a variety of public health issues. By the conclusion of this research based course, students will understand how the various public health perspectives can combine in addressing and informing public health practices.",
      "sections": [
        {
          "sec_code": "0101",
          "instructors": [
            "Kevin Glasz"
          ],
          "class_meetings": [
            {
              "InPerson": {
                "classtime": {
                  "M": [
                    [
                      4,
                      0,
                      "Pm"
                    ],
                    [
                      6,
                      30,
                      "Pm"
                    ]
                  ]
                },
                "location": [
                  "SPH",
                  "0227"
                ]
              }
            }
          ]
        },
        {
          "sec_code": "0201",
          "instructors": [
            "Kendall Bustad"
          ],
          "class_meetings": [
            {
              "InPerson": {
                "classtime": {
                  "M": [
                    [
                      4,
                      0,
                      "Pm"
                    ],
                    [
                      6,
                      30,
                      "Pm"
                    ]
                  ]
                },
                "location": [
                  "ESJ",
                  "B0322"
                ]
              }
            }
          ]
        },
        {
          "sec_code": "0301",
          "instructors": [
            "Kevin Glasz"
          ],
          "class_meetings": [
            {
              "InPerson": {
                "classtime": {
                  "Tu": [
                    [
                      4,
                      0,
                      "Pm"
                    ],
                    [
                      6,
                      30,
                      "Pm"
                    ]
                  ]
                },
                "location": [
                  "SPH",
                  "0227"
                ]
              }
            }
          ]
        },
        {
          "sec_code": "0401",
          "instructors": [
            "Aysha Jawed"
          ],
          "class_meetings": [
            {
              "OnlineSync": {
                "Tu": [
                  [
                    6,
                    0,
                    "Pm"
                  ],
                  [
                    8,
                    30,
                    "Pm"
                  ]
                ]
              }
            }
          ]
        },
        {
          "sec_code": "0501",
          "instructors": [
            "Jennifer German"
          ],
          "class_meetings": [
            {
              "InPerson": {
                "classtime": {
                  "W": [
                    [
                      4,
                      0,
                      "Pm"
                    ],
                    [
                      6,
                      30,
                      "Pm"
                    ]
                  ]
                },
                "location": [
                  "SPH",
                  "0227"
                ]
              }
            }
          ]
        },
        {
          "sec_code": "0601",
          "instructors": [
            "Carmen Booker"
          ],
          "class_meetings": [
            {
              "InPerson": {
                "classtime": {
                  "W": [
                    [
                      6,
                      0,
                      "Pm"
                    ],
                    [
                      8,
                      30,
                      "Pm"
                    ]
                  ]
                },
                "location": [
                  "SPH",
                  "0225"
                ]
              }
            }
          ]
        },
        {
          "sec_code": "0701",
          "instructors": [
            "Lakeshia Watson"
          ],
          "class_meetings": [
            {
              "InPerson": {
                "classtime": {
                  "Th": [
                    [
                      6,
                      0,
                      "Pm"
                    ],
                    [
                      8,
                      30,
                      "Pm"
                    ]
                  ]
                },
                "location": [
                  "SPH",
                  "0305"
                ]
              }
            }
          ]
        },
        {
          "sec_code": "0801",
          "instructors": [
            "Carmen Booker"
          ],
          "class_meetings": [
            {
              "OnlineSync": {
                "M": [
                  [
                    6,
                    0,
                    "Pm"
                  ],
                  [
                    8,
                    30,
                    "Pm"
                  ]
                ]
              }
            }
          ]
        },
        {
          "sec_code": "0901",
          "instructors": [
            "Darya Soltani"
          ],
          "class_meetings": [
            {
              "InPerson": {
                "classtime": {
                  "M": [
                    [
                      5,
                      0,
                      "Pm"
                    ],
                    [
                      7,
                      30,
                      "Pm"
                    ]
                  ]
                },
                "location": [
                  "SPH",
                  "0121"
                ]
              }
            }
          ]
        },
        {
          "sec_code": "1001",
          "instructors": [
            "Lakeshia Watson"
          ],
          "class_meetings": [
            {
              "OnlineSync": {
                "Tu": [
                  [
                    3,
                    0,
                    "Pm"
                  ],
                  [
                    5,
                    30,
                    "Pm"
                  ]
                ]
              }
            }
          ]
        },
        {
          "sec_code": "1101",
          "instructors": [
            "Catherine Sapp"
          ],
          "class_meetings": [
            {
              "InPerson": {
                "classtime": {
                  "Th": [
                    [
                      4,
                      0,
                      "Pm"
                    ],
                    [
                      6,
                      30,
                      "Pm"
                    ]
                  ]
                },
                "location": [
                  "SPH",
                  "0227"
                ]
              }
            }
          ]
        },
        {
          "sec_code": "1201",
          "instructors": [
            "Eric Silfen"
          ],
          "class_meetings": [
            {
              "OnlineSync": {
                "Tu": [
                  [
                    6,
                    0,
                    "Pm"
                  ],
                  [
                    8,
                    30,
                    "Pm"
                  ]
                ]
              }
            }
          ]
        },
        {
          "sec_code": "1",
          "instructors": [
            "Ann Truelove"
          ],
          "class_meetings": [
            {
              "InPerson": {
                "classtime": {
                  "Th": [
                    [
                      4,
                      30,
                      "Pm"
                    ],
                    [
                      7,
                      0,
                      "Pm"
                    ]
                  ]
                },
                "location": null
              }
            }
          ]
        }
      ]
    }
  ]
}