{
  "name": "EDMS",
  "courses": [
    {
      "code": "EDMS451",
      "name": "Introduction to Educational Statistics",
      "credits": {
        "Amount": 3
      },
      "gen_eds": [
        "FSAR"
      ],
      "description": "Introduction to statistical reasoning; location and dispersion measures; computer applications; regression and correlation; formation of hypotheses tests; t-test; one-way analysis of variance; analysis of contingency tables.",
      "sections": [
        {
          "sec_code": "0101",
          "instructors": [
            "Dayeon Lee"
          ],
          "class_meetings": [
            {
              "InPerson": {
                "classtime": {
                  "TuTh": [
                    [
                      12,
                      30,
                      "Pm"
                    ],
                    [
                      1,
                      45,
                      "Pm"
                    ]
                  ]
                },
                "location": [
                  "EDU",
                  "1121"
                ]
              }
            }
          ]
        },
        {
          "sec_code": "0201",
          "instructors": [
            "Marieh Arnett"
          ],
          "class_meetings": [
            {
              "InPerson": {
                "classtime": {
                  "MW": [
                    [
                      11,
                      0,
                      "Am"
                    ],
                    [
                      12,
                      15,
                      "Pm"
                    ]
                  ]
                },
                "location": [
                  "EDU",
                  "3315"
                ]
              }
            }
          ]
        }
      ]
    },
    {
      "code": "EDMS645",
      "name": "Quantitative Research Methods I",
      "credits": {
        "Amount": 3
      },
      "gen_eds": null,
      "description": "Research design and statistical applications in educational research: data representation; descriptive statistics; estimation and hypothesis testing. Application of statistical computer packages is emphasized.",
      "sections": [
        {
          "sec_code": "0101",
          "instructors": [
            "Weimeng Wang"
          ],
          "class_meetings": [
            {
              "InPerson": {
                "classtime": {
                  "M": [
                    [
                      4,
                      15,
                      "Pm"
                    ],
                    [
                      7,
                      0,
                      "Pm"
                    ]
                  ]
                },
                "location": [
                  "LEF",
                  "1220"
                ]
              }
            }
          ]
        }
      ]
    },
    {
      "code": "EDMS646",
      "name": "General Linear Models I",
      "credits": {
        "Amount": 3
      },
      "gen_eds": null,
      "description": "A first post-introductory inferential statistics course, with emphasis on analysis of variance procedures and designs from within the general linear modeling framework. Assignments include student analysis of education and related data; application of statistical software packages is emphasized.",
      "sections": [
        {
          "sec_code": "0101",
          "instructors": [
            "Jeffrey Harring"
          ],
          "class_meetings": [
            {
              "InPerson": {
                "classtime": {
                  "W": [
                    [
                      4,
                      15,
                      "Pm"
                    ],
                    [
                      7,
                      0,
                      "Pm"
                    ]
                  ]
                },
                "location": [
                  "EDU",
                  "3315"
                ]
              }
            }
          ]
        }
      ]
    },
    {
      "code": "EDMS647",
      "name": "Causal Inference and Evaluation Methods",
      "credits": {
        "Amount": 3
      },
      "gen_eds": null,
      "description": "Counterfactual (potential outcomes) framework for causal inference, design/analysis strategies for confounder control, and specific best-practice applications to the evaluation of programs.",
      "sections": [
        {
          "sec_code": "0101",
          "instructors": [
            "Peter Steiner"
          ],
          "class_meetings": [
            {
              "InPerson": {
                "classtime": {
                  "Tu": [
                    [
                      4,
                      15,
                      "Pm"
                    ],
                    [
                      7,
                      0,
                      "Pm"
                    ]
                  ]
                },
                "location": [
                  "EDU",
                  "2119"
                ]
              }
            }
          ]
        }
      ]
    },
    {
      "code": "EDMS651",
      "name": "General Linear Models II",
      "credits": {
        "Amount": 3
      },
      "gen_eds": null,
      "description": "Multiple regression and correlation analysis; trend analysis; hierarchical and stepwise procedures; logistic regression; software for regression analysis.",
      "sections": [
        {
          "sec_code": "0101",
          "instructors": [
            "Yang Liu"
          ],
          "class_meetings": [
            {
              "InPerson": {
                "classtime": {
                  "M": [
                    [
                      4,
                      15,
                      "Pm"
                    ],
                    [
                      7,
                      0,
                      "Pm"
                    ]
                  ]
                },
                "location": [
                  "EDU",
                  "1121"
                ]
              }
            }
          ]
        }
      ]
    },
    {
      "code": "EDMS722",
      "name": "Structural Modeling",
      "credits": {
        "Amount": 3
      },
      "gen_eds": null,
      "description": "Statistical theory and methods of estimation used in structural modeling; computer program applications; multisample models; mean structture models; structural models with multilevel data (e.g., sampling weights, growth models, multilevel latent variable models).",
      "sections": [
        {
          "sec_code": "0101",
          "instructors": [
            "Gregory Hancock"
          ],
          "class_meetings": [
            {
              "InPerson": {
                "classtime": {
                  "Tu": [
                    [
                      4,
                      15,
                      "Pm"
                    ],
                    [
                      7,
                      0,
                      "Pm"
                    ]
                  ]
                },
                "location": [
                  "EDU",
                  "1121"
                ]
              }
            }
          ]
        }
      ]
    },
    {
      "code": "EDMS724",
      "name": "Modern Measurement Theory",
      "credits": {
        "Amount": 3
      },
      "gen_eds": null,
      "description": "Theoretical formulations of measurement from a latent trait theory perspective.",
      "sections": [
        {
          "sec_code": "0101",
          "instructors": [
            "Hong Jiao"
          ],
          "class_meetings": [
            {
              "InPerson": {
                "classtime": {
                  "W": [
                    [
                      4,
                      15,
                      "Pm"
                    ],
                    [
                      7,
                      0,
                      "Pm"
                    ]
                  ]
                },
                "location": [
                  "JMZ",
                  "0120"
                ]
              }
            }
          ]
        }
      ]
    },
    {
      "code": "EDMS769L",
      "name": "Special Topics in Applied Statistics in Education; Advanced Longitudinal Models",
      "credits": {
        "Amount": 3
      },
      "gen_eds": null,
      "description": "",
      "sections": [
        {
          "sec_code": "0101",
          "instructors": [
            "Jeffrey Harring"
          ],
          "class_meetings": [
            {
              "InPerson": {
                "classtime": {
                  "Th": [
                    [
                      4,
                      15,
                      "Pm"
                    ],
                    [
                      7,
                      0,
                      "Pm"
                    ]
                  ]
                },
                "location": [
                  "EDU",
                  "2102"
                ]
              }
            }
          ]
        }
      ]
    },
    {
      "code": "EDMS787",
      "name": "Bayesian Inference and Analysis",
      "credits": {
        "Amount": 3
      },
      "gen_eds": null,
      "description": "Models and model fitting methods commonly used in Bayesian Inference, such as Markov Chain Monte Carlo methods (e.g., Gibbs, Metropolis Sampling), with applications within and beyond the social and behavioral sciences. Analytical and philosophical differences between Frequentist and Bayesian statistics will also be highlighted.",
      "sections": [
        {
          "sec_code": "0101",
          "instructors": [
            "Tracy Sweet"
          ],
          "class_meetings": [
            {
              "InPerson": {
                "classtime": {
                  "M": [
                    [
                      4,
                      15,
                      "Pm"
                    ],
                    [
                      7,
                      0,
                      "Pm"
                    ]
                  ]
                },
                "location": [
                  "EDU",
                  "3236"
                ]
              }
            }
          ]
        }
      ]
    },
    {
      "code": "EDMS798",
      "name": "Special Problems in Education",
      "credits": {
        "Range": [
          1,
          6
        ]
      },
      "gen_eds": null,
      "description": "Prerequisite: permission of department.",
      "sections": null
    },
    {
      "code": "EDMS799",
      "name": "Master's Thesis Research",
      "credits": {
        "Range": [
          1,
          6
        ]
      },
      "gen_eds": null,
      "description": "",
      "sections": null
    },
    {
      "code": "EDMS889",
      "name": "Internship in Measurement and Statistics",
      "credits": {
        "Range": [
          3,
          8
        ]
      },
      "gen_eds": null,
      "description": "",
      "sections": null
    },
    {
      "code": "EDMS898",
      "name": "Pre-Candidacy Research",
      "credits": {
        "Range": [
          1,
          8
        ]
      },
      "gen_eds": null,
      "description": "",
      "sections": null
    },
    {
      "code": "EDMS899",
      "name": "Doctoral Dissertation Research",
      "credits": {
        "Amount": 6
      },
      "gen_eds": null,
      "description": "",
      "sections": null
    }
  ]
}